rrfuncat/__init__.py
rrfuncat/api.py
rrfuncat/cmds.py
rrfuncat/context.py
rrfuncat/data/__init__.py
rrfuncat/data/backend.py
rrfuncat/data/tushare_backend.py
rrfuncat/func.py
rrfuncat/get_version.py
rrfuncat/helper.py
rrfuncat/indicators.py
rrfuncat/time_series.py
rrfuncat/utils.py
rrfuncat-0.3.5.dist-info/entry_points.txt
rrfuncat-0.3.5.dist-info/WHEEL
rrfuncat-0.3.5.dist-info/METADATA
rrfuncat-0.3.5.dist-info/RECORD
